mic/__init__.py
mic/__main__.py
mic/_utils.py
mic/cli_docs.py
mic/commands_notebook.py
mic/config_yaml.py
mic/constants.py
mic/credentials.py
mic/drawer.py
mic/model_catalog_utils.py
mic/ notebook/__init__.py
mic/click_encapsulate/__init__.py
mic/click_encapsulate/commands.py
mic/component/__init__.py
mic/component/detect.py
mic/component/executor.py
mic/component/initialization.py
mic/component/python3.py
mic/component/reprozip.py
mic/cwl/__init__.py
mic/cwl/cwl.py
mic/publisher/__init__.py
mic/publisher/docker.py
mic/publisher/model_catalog.py
mic/publisher/s3.py
mic/resources/__init__.py
mic/resources/data_specification.py
mic/resources/data_transformation.py
mic/resources/image.py
mic/resources/model.py
mic/resources/model_configuration.py
mic/resources/model_configuration_setup.py
mic/resources/parameter.py
mic/resources/person.py
mic/resources/sample_resource.py
mic/resources/software_version.py
mic/templates/.colors.sh
mic/templates/.gitignore
mic/templates/Dockerfile
mic/templates/entrypoint.sh
mic/templates/environment.yml
mic/templates/install.sh
mic/templates/io.sh
mic/templates/mic_run_file
mic/templates/output.sh
mic/templates/run
mic-2.2.1.dist-info/METADATA
mic-2.2.1.dist-info/WHEEL
mic-2.2.1.dist-info/entry_points.txt
mic-2.2.1.dist-info/top_level.txt
mic-2.2.1.dist-info/RECORD
