Metadata-Version: 2.1
Name: mic
Version: 2.2.1
Summary: UNKNOWN
Home-page: https://github.com/mintproject/mic
Author: Maximiliano Osorio
Author-email: mosorio@isi.edu
License: Apache-2
Platform: UNKNOWN
Classifier: License :: OSI Approved :: Apache Software License
Classifier: Development Status :: 3 - Alpha
Classifier: Programming Language :: Python
Classifier: Programming Language :: Python :: 3
Classifier: Programming Language :: Python :: 3.5
Classifier: Programming Language :: Python :: 3.6
Classifier: Programming Language :: Python :: 3.7
Classifier: Intended Audience :: Science/Research
Classifier: Operating System :: Unix
Requires-Python: >=3.5.0
Requires-Dist: Click (>=7.0)
Requires-Dist: jsonschema (>=3.0.0)
Requires-Dist: semver (>=2.8.1)
Requires-Dist: requests
Requires-Dist: tabulate (>=0.8.1)
Requires-Dist: Jinja2 (>=2.11.2)
Requires-Dist: PyYAML (>=5.3.1)
Requires-Dist: modelcatalog-api (==8.0.0)
Requires-Dist: ipython2cwlmosorio (==0.0.5)
Requires-Dist: validators
Requires-Dist: mint-upload
